nfl/__init__.py
nfl/main.py
python-nfl/__init__.py
python-nfl/main.py
lib_nfl-1.0.0.dist-info/METADATA
lib_nfl-1.0.0.dist-info/WHEEL
lib_nfl-1.0.0.dist-info/top_level.txt
lib_nfl-1.0.0.dist-info/RECORD
