Metadata-Version: 2.1
Name: lib-nfl
Version: 1.0.0
Summary: NFL is a number formatting library.
Home-page: https://github.com/DDavid701/nfl
Author: DDavid701
Author-email: ddavid701@gmail.com
Classifier: Programming Language :: Python :: 3
Classifier: License :: OSI Approved :: MIT License
Classifier: Operating System :: OS Independent
Requires-Python: >=3.10
